microndla/__init__.py
microndla/microndla.py
microndla/onnx_optim.py
microndla/onnx_util.py
microndla-2022.1.dist-info/LICENSE.md
microndla-2022.1.dist-info/METADATA
microndla-2022.1.dist-info/WHEEL
microndla-2022.1.dist-info/top_level.txt
microndla-2022.1.dist-info/RECORD
