Metadata-Version: 2.1
Name: microndla
Version: 2022.1
Summary: Micron Deep Learning Acceleration SDK
Home-page: https://github.com/FWDNXT/SDK
Author: Micron
License: UNKNOWN
Platform: UNKNOWN
License-File: LICENSE.md
Requires-Dist: numpy (>=1.14.2)
Requires-Dist: Pillow (>=5.0)
Requires-Dist: onnx (>=1.8.1)
Requires-Dist: onnx-simplifier
